Metadata-Version: 1.0
Name: baresipy
Version: 0.1.4
Summary: python baresip wrapper
Home-page: https://github.com/JarbasAl/baresipy
Author: jarbasAI
Author-email: jarbasai@mailfence.com
License: MIT
Platform: UNKNOWN
